setup.py
pylocks/__init__.py
pylocks/conf.py
pylocks/errors.py
pylocks/serialization.py
pylocks/util.py
pylocks.egg-info/PKG-INFO
pylocks.egg-info/SOURCES.txt
pylocks.egg-info/dependency_links.txt
pylocks.egg-info/requires.txt
pylocks.egg-info/top_level.txt
pylocks/blocking/__init__.py
pylocks/blocking/base_blocking_redis_lock.py
pylocks/blocking/blocking_redis_lease_handle.py
pylocks/blocking/blocking_redis_lock.py
pylocks/core/__init__.py
pylocks/core/key_formatter.py
pylocks/core/lock_lease_data.py
pylocks/core/lock_request.py
pylocks/core/lock_settings.py
pylocks/test/__init__.py
pylocks/test/errors.py
pylocks/test/redis_test.py
pylocks/test/test_serialization.py
pylocks/test/blocking/__init__.py
pylocks/test/blocking/test_base_blocking_redis_lock.py
pylocks/test/blocking/test_blocking_redis_lease_handle.py
pylocks/test/blocking/test_blocking_redis_lock.py
pylocks/test/core/__init__.py
pylocks/test/core/test_key_formatter.py
pylocks/test/core/test_lock_lease_data.py
pylocks/test/core/test_lock_settings.py