Metadata-Version: 1.1
Name: pylocks
Version: 0.2.1
Summary: redis-backed locks and leases
Home-page: UNKNOWN
Author: Scott Ivey
Author-email: scott.ivey@gmail.com
License: MIT
Platform: UNKNOWN
Classifier: License :: OSI Approved :: MIT License
Classifier: Intended Audience :: Developers
Classifier: Programming Language :: Python :: 3
